uframe/__init__.py
uframe/helper.py
uframe/uframe.py
uframe/uframe_from_mice.py
uframe/uframe_instance.py
uframe/utils.py
uframe-0.0.25.dist-info/LICENSE
uframe-0.0.25.dist-info/METADATA
uframe-0.0.25.dist-info/WHEEL
uframe-0.0.25.dist-info/top_level.txt
uframe-0.0.25.dist-info/RECORD
