Metadata-Version: 2.1
Name: uframe
Version: 0.0.25
Summary: Package for handling uncertain data
Author: Christian Amesoeder and Michael Hagn
Author-email: Christian Amesoder <christian.amesoeder@informatik.uni-regensburg.de>, Michael Hagn <michael.hagn@stud.uni-regensburg.de>
Project-URL: Homepage, https://github.com/URWI2/uframe
Classifier: Programming Language :: Python :: 3
Classifier: License :: OSI Approved :: MIT License
Classifier: Operating System :: OS Independent
Requires-Python: >=3.7
License-File: LICENSE
Requires-Dist: scipy (>=1.9.3)
Requires-Dist: scikit-learn (>=1.2.0)
Requires-Dist: numpy (>=1.23.5)
Requires-Dist: matplotlib
Requires-Dist: miceforest
Requires-Dist: seaborn
Provides-Extra: testing
Requires-Dist: pytest (>=6.0) ; extra == 'testing'
Requires-Dist: pytest-cov (>=2.0) ; extra == 'testing'
Requires-Dist: mypy (>=0.910) ; extra == 'testing'
Requires-Dist: flake8 (>=3.9) ; extra == 'testing'
Requires-Dist: tox (>=3.24) ; extra == 'testing'
Provides-Extra: tests
Requires-Dist: pytest-cov ; extra == 'tests'
Requires-Dist: pytest (>=7.3.1) ; extra == 'tests'
Requires-Dist: coverage (>=4.5.4) ; extra == 'tests'
Requires-Dist: tox (>=3.14.0) ; extra == 'tests'
Requires-Dist: flake8 (>=3.7.8) ; extra == 'tests'
Requires-Dist: wheel (>=0.33.6) ; extra == 'tests'
Requires-Dist: pip (>=19.2.3) ; extra == 'tests'
